tklfp/__init__.py
tklfp/exc_A0_by_depth.pkl
tklfp/inh_A0_by_depth.pkl
tklfp-0.2.1.dist-info/LICENSE
tklfp-0.2.1.dist-info/METADATA
tklfp-0.2.1.dist-info/WHEEL
tklfp-0.2.1.dist-info/top_level.txt
tklfp-0.2.1.dist-info/RECORD
