Metadata-Version: 2.1
Name: tklfp
Version: 0.2.1
Summary: A minimal package for computing the kernel LFP approximation from Telenczuk et al., 2020
Home-page: https://github.com/kjohnsen/tklfp/tree/master/
Author: Kyle Johnsen
Author-email: kjohnsen@gatech.edu
License: Apache Software License 2.0
Keywords: neuroscience kernel LFP Telenczuk spikes
Classifier: Development Status :: 4 - Beta
Classifier: Intended Audience :: Science/Research
Classifier: License :: OSI Approved :: Apache Software License
Classifier: Natural Language :: English
Classifier: Programming Language :: Python :: 3.9
Classifier: Programming Language :: Python :: 3.10
Classifier: Programming Language :: Python :: 3.11
Classifier: Programming Language :: Python :: 3.12
Requires-Python: >=3.9
License-File: LICENSE
Requires-Dist: numpy
Requires-Dist: scipy
Requires-Dist: importlib-resources
